anthunder/__init__.py
anthunder/exceptions.py
anthunder/request.py
anthunder/client/__init__.py
anthunder/client/aio_client.py
anthunder/client/base.py
anthunder/client/client.py
anthunder/command/__init__.py
anthunder/command/fail_response.py
anthunder/command/heartbeat.py
anthunder/helpers/__init__.py
anthunder/helpers/immutable_dict.py
anthunder/helpers/request_id.py
anthunder/helpers/singleton.py
anthunder/listener/__init__.py
anthunder/listener/aio_listener.py
anthunder/listener/base_listener.py
anthunder/listener/sock_listener.py
anthunder/mesh/__init__.py
anthunder/mesh/mesh_client.py
anthunder/protocol/__init__.py
anthunder/protocol/_package_base.py
anthunder/protocol/_request_pkg.py
anthunder/protocol/_response_pkg.py
anthunder/protocol/_rpc_trace_context.py
anthunder/protocol/_sofa_header.py
anthunder/protocol/constants.py
anthunder/protocol/exceptions.py
mysockpool/__init__.py
mysockpool/_wait.py
mysockpool/connection.py
mysockpool/connection_pool.py
mysockpool/exceptions.py
mysockpool/origin-license.txt
mysockpool/pool_manager.py
mysockpool/recently_used_container.py
mysockpool/utils.py
mytracer/__init__.py
mytracer/_rpc_id.py
mytracer/_trace_id.py
mytracer/helpers.py
mytracer/span.py
mytracer/span_context.py
mytracer/tracer.py
anthunder-0.8.1.dist-info/LICENSE
anthunder-0.8.1.dist-info/METADATA
anthunder-0.8.1.dist-info/WHEEL
anthunder-0.8.1.dist-info/top_level.txt
anthunder-0.8.1.dist-info/RECORD
