Metadata-Version: 2.1
Name: anthunder
Version: 0.8.1
Summary: an(t)thunder is a sofa-bolt protocol lib.
Home-page: https://github.com/alipay/sofa-bolt-python
Author: wanderxjtu
Author-email: wanderhuang@gmail.com
License: Apache License 2.0
Platform: UNKNOWN
Classifier: Development Status :: 4 - Beta
Classifier: Intended Audience :: Developers
Classifier: Natural Language :: English
Classifier: License :: OSI Approved :: Apache Software License
Classifier: Programming Language :: Python
Classifier: Programming Language :: Python :: 2
Classifier: Programming Language :: Python :: 2.7
Classifier: Programming Language :: Python :: 3
Classifier: Programming Language :: Python :: 3.5
Classifier: Programming Language :: Python :: 3.6
Classifier: Programming Language :: Python :: 3.7
Classifier: Programming Language :: Python :: Implementation :: CPython
Classifier: Programming Language :: Python :: Implementation :: PyPy
Requires-Dist: opentracing (==1.3.0)
Requires-Dist: requests (>=2.13.0)
Requires-Dist: attrs (>=18.1.0)
Requires-Dist: six
